wlang_cli/__main__.py
wlang_cli-0.1.4.dist-info/LICENSE
wlang_cli-0.1.4.dist-info/WHEEL
wlang_cli-0.1.4.dist-info/METADATA
wlang_cli-0.1.4.dist-info/RECORD
