Metadata-Version: 2.1
Name: wlang-cli
Version: 0.1.4
Summary: A cli for the W programming language
License: MIT
Author: James Butcher
Author-email: jamesbutcher@duck.com
Requires-Python: >=3.7
Classifier: License :: OSI Approved :: MIT License
Classifier: Programming Language :: Python :: 3
Classifier: Programming Language :: Python :: 3.10
Classifier: Programming Language :: Python :: 3.7
Classifier: Programming Language :: Python :: 3.8
Classifier: Programming Language :: Python :: 3.9
Requires-Dist: click (>=8.1.0,<9.0.0)
Requires-Dist: wcore-py (>=0.5.1,<0.6.0)
